setup.cfg
setup.py
TOPSIS_AnurupBansal_101816043.egg-info/PKG-INFO
TOPSIS_AnurupBansal_101816043.egg-info/SOURCES.txt
TOPSIS_AnurupBansal_101816043.egg-info/dependency_links.txt
TOPSIS_AnurupBansal_101816043.egg-info/entry_points.txt
TOPSIS_AnurupBansal_101816043.egg-info/requires.txt
TOPSIS_AnurupBansal_101816043.egg-info/top_level.txt
source/topsis.py