Metadata-Version: 1.1
Name: TOPSIS-AnurupBansal-101816043
Version: 1.0.1
Summary: This is a Python package to implement TOPSIS technique.
Home-page: https://pypi.org/project/TOPSIS-AnurupBansal-101816043
Author: Anurup Bansal
Author-email: anurupbansal@gmail.com
License: MIT
Platform: UNKNOWN
Classifier: License :: OSI Approved :: MIT License
Classifier: Programming Language :: Python :: 3
Classifier: Programming Language :: Python :: 3.4
Classifier: Programming Language :: Python :: 3.5
Classifier: Programming Language :: Python :: 3.6
Classifier: Programming Language :: Python :: 3.7
